LICENSE.txt
MANIFEST.in
README.md
setup.py
jk_git/AbstractRepositoryFile.py
jk_git/GitCommitHistory.py
jk_git/GitCommitHistoryEntry.py
jk_git/GitConfigFile.py
jk_git/GitFileInfo.py
jk_git/GitRemoteRepository.py
jk_git/GitServerRepository.py
jk_git/GitWorkingCopy.py
jk_git/GitWrapper.py
jk_git/__init__.py
jk_git.egg-info/PKG-INFO
jk_git.egg-info/SOURCES.txt
jk_git.egg-info/dependency_links.txt
jk_git.egg-info/not-zip-safe
jk_git.egg-info/requires.txt
jk_git.egg-info/top_level.txt
jk_git/impl/GitConfigFile.py
jk_git/impl/GitConfigFileSection.py
jk_git/impl/GitHelper.py
jk_git/impl/__init__.py
jk_git/workingcopy/_GitStatusOutputParser.py
jk_git/workingcopy/__init__.py