Metadata-Version: 2.1
Name: jk-git
Version: 0.2022.7.24
Summary: This python module is a wrapper around git (= the git binary file). It is ment as a simple interface to basic git functionality.
Home-page: UNKNOWN
Author: Jürgen Knauth
Author-email: pubsrc@binary-overflow.de
License: Apache2
Keywords: git
Platform: UNKNOWN
Classifier: Development Status :: 4 - Beta
Classifier: License :: OSI Approved :: Apache Software License
Classifier: Programming Language :: Python :: 3
